MaxOS/__init__.py
MaxOS/module.py
MaxOS-1.1.0.dist-info/METADATA
MaxOS-1.1.0.dist-info/WHEEL
MaxOS-1.1.0.dist-info/top_level.txt
MaxOS-1.1.0.dist-info/RECORD
