Metadata-Version: 2.1
Name: MaxOS
Version: 1.1.0
Summary: MaxOS library
Home-page: 
Author: fhghfhfhfh
Author-email: maximdev@internet.ru
Classifier: Programming Language :: Python :: 3
Classifier: License :: OSI Approved :: MIT License
